{
    "key": "group_5cb2411aa7d43",
    "title": "Header Fields",
    "fields": [
        {
            "key": "field_5cb24132e309a",
            "label": "Logo",
            "name": "logo",
            "type": "image",
            "instructions": "",
            "required": 0,
            "conditional_logic": 0,
            "wrapper": {
                "width": "",
                "class": "",
                "id": ""
            },
            "return_format": "array",
            "preview_size": "thumbnail",
            "library": "all",
            "min_width": "",
            "min_height": "",
            "min_size": "",
            "max_width": "",
            "max_height": "",
            "max_size": "",
            "mime_types": ""
        },
        {
            "key": "field_5cb241bd99515",
            "label": "Cart Icon",
            "name": "cart_icon",
            "type": "font-awesome",
            "instructions": "",
            "required": 0,
            "conditional_logic": 0,
            "wrapper": {
                "width": "",
                "class": "",
                "id": ""
            },
            "icon_sets": [
                "far",
                "fal"
            ],
            "custom_icon_set": "",
            "default_label": "",
            "default_value": "",
            "save_format": "element",
            "allow_null": 0,
            "show_preview": 1,
            "enqueue_fa": 0,
            "fa_live_preview": "",
            "choices": []
        },
        {
            "key": "field_5cb241d93add9",
            "label": "My Account Icon",
            "name": "my_account_icon",
            "type": "font-awesome",
            "instructions": "",
            "required": 0,
            "conditional_logic": 0,
            "wrapper": {
                "width": "",
                "class": "",
                "id": ""
            },
            "icon_sets": [
                "far",
                "fal"
            ],
            "custom_icon_set": "",
            "default_label": "",
            "default_value": "",
            "save_format": "element",
            "allow_null": 0,
            "show_preview": 1,
            "enqueue_fa": 0,
            "fa_live_preview": "",
            "choices": []
        },
        {
            "key": "field_5d811a0d0fdbf",
            "label": "Tracking Scripts",
            "name": "header_tracking_scripts",
            "type": "textarea",
            "instructions": "",
            "required": 0,
            "conditional_logic": 0,
            "wrapper": {
                "width": "",
                "class": "",
                "id": ""
            },
            "default_value": "",
            "placeholder": "",
            "maxlength": "",
            "rows": "",
            "new_lines": ""
        }
    ],
    "location": [
        [
            {
                "param": "options_page",
                "operator": "==",
                "value": "header"
            }
        ]
    ],
    "menu_order": 9,
    "position": "normal",
    "style": "default",
    "label_placement": "top",
    "instruction_placement": "label",
    "hide_on_screen": "",
    "active": 1,
    "description": "",
    "modified": 1568741935
}